music/__init__.py
music/info.py
music/player.py
music/queue.py
chillyfy-0.1.0.dist-info/METADATA
chillyfy-0.1.0.dist-info/WHEEL
chillyfy-0.1.0.dist-info/top_level.txt
chillyfy-0.1.0.dist-info/RECORD
