Metadata-Version: 2.1
Name: chillyfy
Version: 0.1.0
Summary: Una libreria per creare bot musicali su Discord
Home-page: https://github.com/ChillatoDevOfficial/chillyfy
Author: ChillatoDev
Author-email: voipfra303@gmail.com
Classifier: Programming Language :: Python :: 3
Classifier: License :: OSI Approved :: MIT License
Classifier: Operating System :: OS Independent
Requires-Dist: discord.py[voice]
Requires-Dist: yt-dlp
Requires-Dist: PyNaCl
